[
  {
    "id": "Alto_Alegre_Estupro_2026_Janeiro",
    "regiao": "Araçatuba",
    "municipio": "Alto Alegre",
    "tipo_crime": "Estupro",
    "ano": "2026",
    "mes": "Janeiro",
    "ocorrencias": 0,
    "variacao_mensal": 0.0
  },
  {
    "id": "Alto_Alegre_Estupro_2026_Abril",
    "regiao": "Araçatuba",
    "municipio": "Alto Alegre",
    "tipo_crime": "Estupro",
    "ano": "2026",
    "mes": "Abril",
    "ocorrencias": 0,
    "variacao_mensal": 0.0
  },
  {
    "id": "Alto_Alegre_Estupro_2026_Julho",
    "regiao": "Araçatuba",
    "municipio": "Alto Alegre",
    "tipo_crime": "Estupro",
    "ano": "2026",
    "mes": "Julho",
    "ocorrencias": 0,
    "variacao_mensal": 0.0
  },
  {
    "id": "Alto_Alegre_Estupro_2026_Outubro",
    "regiao": "Araçatuba",
    "municipio": "Alto Alegre",
    "tipo_crime": "Estupro",
    "ano": "2026",
    "mes": "Outubro",
    "ocorrencias": 0,
    "variacao_mensal": 0.0
  },
  {
    "id": "Alto_Alegre_Estupro_De_Vulnerável_2026_Janeiro",
    "regiao": "Araçatuba",
    "municipio": "Alto Alegre",
    "tipo_crime": "Estupro De Vulnerável",
    "ano": "2026",
    "mes": "Janeiro",
    "ocorrencias": 0,
    "variacao_mensal": 0.0
  },
  {
    "id": "Alto_Alegre_Estupro_De_Vulnerável_2026_Abril",
    "regiao": "Araçatuba",
    "municipio": "Alto Alegre",
    "tipo_crime": "Estupro De Vulnerável",
    "ano": "2026",
    "mes": "Abril",
    "ocorrencias": 0,
    "variacao_mensal": 0.0
  },
  {
    "id": "Alto_Alegre_Estupro_De_Vulnerável_2026_Julho",
    "regiao": "Araçatuba",
    "municipio": "Alto Alegre",
    "tipo_crime": "Estupro De Vulnerável",
    "ano": "2026",
    "mes": "Julho",
    "ocorrencias": 0,
    "variacao_mensal": 0.0
  },
  {
    "id": "Alto_Alegre_Estupro_De_Vulnerável_2026_Outubro",
    "regiao": "Araçatuba",
    "municipio": "Alto Alegre",
    "tipo_crime": "Estupro De Vulnerável",
    "ano": "2026",
    "mes": "Outubro",
    "ocorrencias": 0,
    "variacao_mensal": 0.0
  },
  {
    "id": "Alto_Alegre_Furto_-_Outros_2026_Janeiro",
    "regiao": "Araçatuba",
    "municipio": "Alto Alegre",
    "tipo_crime": "Furto - Outros",
    "ano": "2026",
    "mes": "Janeiro",
    "ocorrencias": 4,
    "variacao_mensal": 0.0
  },
  {
    "id": "Alto_Alegre_Furto_-_Outros_2026_Abril",
    "regiao": "Araçatuba",
    "municipio": "Alto Alegre",
    "tipo_crime": "Furto - Outros",
    "ano": "2026",
    "mes": "Abril",
    "ocorrencias": 1,
    "variacao_mensal": -75.0
  },
  {
    "id": "Alto_Alegre_Furto_-_Outros_2026_Julho",
    "regiao": "Araçatuba",
    "municipio": "Alto Alegre",
    "tipo_crime": "Furto - Outros",
    "ano": "2026",
    "mes": "Julho",
    "ocorrencias": 0,
    "variacao_mensal": -100.0
  },
  {
    "id": "Alto_Alegre_Furto_-_Outros_2026_Outubro",
    "regiao": "Araçatuba",
    "municipio": "Alto Alegre",
    "tipo_crime": "Furto - Outros",
    "ano": "2026",
    "mes": "Outubro",
    "ocorrencias": 0,
    "variacao_mensal": 0.0
  },
  {
    "id": "Alto_Alegre_Furto_De_Veículo_2026_Janeiro",
    "regiao": "Araçatuba",
    "municipio": "Alto Alegre",
    "tipo_crime": "Furto De Veículo",
    "ano": "2026",
    "mes": "Janeiro",
    "ocorrencias": 0,
    "variacao_mensal": 0.0
  },
  {
    "id": "Alto_Alegre_Furto_De_Veículo_2026_Abril",
    "regiao": "Araçatuba",
    "municipio": "Alto Alegre",
    "tipo_crime": "Furto De Veículo",
    "ano": "2026",
    "mes": "Abril",
    "ocorrencias": 0,
    "variacao_mensal": 0.0
  },
  {
    "id": "Alto_Alegre_Furto_De_Veículo_2026_Julho",
    "regiao": "Araçatuba",
    "municipio": "Alto Alegre",
    "tipo_crime": "Furto De Veículo",
    "ano": "2026",
    "mes": "Julho",
    "ocorrencias": 0,
    "variacao_mensal": 0.0
  },
  {
    "id": "Alto_Alegre_Furto_De_Veículo_2026_Outubro",
    "regiao": "Araçatuba",
    "municipio": "Alto Alegre",
    "tipo_crime": "Furto De Veículo",
    "ano": "2026",
    "mes": "Outubro",
    "ocorrencias": 0,
    "variacao_mensal": 0.0
  },
  {
    "id": "Alto_Alegre_Homicídio_Culposo_Outros_2026_Janeiro",
    "regiao": "Araçatuba",
    "municipio": "Alto Alegre",
    "tipo_crime": "Homicídio Culposo Outros",
    "ano": "2026",
    "mes": "Janeiro",
    "ocorrencias": 0,
    "variacao_mensal": 0.0
  },
  {
    "id": "Alto_Alegre_Homicídio_Culposo_Outros_2026_Abril",
    "regiao": "Araçatuba",
    "municipio": "Alto Alegre",
    "tipo_crime": "Homicídio Culposo Outros",
    "ano": "2026",
    "mes": "Abril",
    "ocorrencias": 0,
    "variacao_mensal": 0.0
  },
  {
    "id": "Alto_Alegre_Homicídio_Culposo_Outros_2026_Julho",
    "regiao": "Araçatuba",
    "municipio": "Alto Alegre",
    "tipo_crime": "Homicídio Culposo Outros",
    "ano": "2026",
    "mes": "Julho",
    "ocorrencias": 0,
    "variacao_mensal": 0.0
  },
  {
    "id": "Alto_Alegre_Homicídio_Culposo_Outros_2026_Outubro",
    "regiao": "Araçatuba",
    "municipio": "Alto Alegre",
    "tipo_crime": "Homicídio Culposo Outros",
    "ano": "2026",
    "mes": "Outubro",
    "ocorrencias": 0,
    "variacao_mensal": 0.0
  },
  {
    "id": "Alto_Alegre_Homicídio_Culposo_Por_Acidente_De_Trânsito_2026_Janeiro",
    "regiao": "Araçatuba",
    "municipio": "Alto Alegre",
    "tipo_crime": "Homicídio Culposo Por Acidente De Trânsito",
    "ano": "2026",
    "mes": "Janeiro",
    "ocorrencias": 0,
    "variacao_mensal": 0.0
  },
  {
    "id": "Alto_Alegre_Homicídio_Culposo_Por_Acidente_De_Trânsito_2026_Abril",
    "regiao": "Araçatuba",
    "municipio": "Alto Alegre",
    "tipo_crime": "Homicídio Culposo Por Acidente De Trânsito",
    "ano": "2026",
    "mes": "Abril",
    "ocorrencias": 0,
    "variacao_mensal": 0.0
  },
  {
    "id": "Alto_Alegre_Homicídio_Culposo_Por_Acidente_De_Trânsito_2026_Julho",
    "regiao": "Araçatuba",
    "municipio": "Alto Alegre",
    "tipo_crime": "Homicídio Culposo Por Acidente De Trânsito",
    "ano": "2026",
    "mes": "Julho",
    "ocorrencias": 0,
    "variacao_mensal": 0.0
  },
  {
    "id": "Alto_Alegre_Homicídio_Culposo_Por_Acidente_De_Trânsito_2026_Outubro",
    "regiao": "Araçatuba",
    "municipio": "Alto Alegre",
    "tipo_crime": "Homicídio Culposo Por Acidente De Trânsito",
    "ano": "2026",
    "mes": "Outubro",
    "ocorrencias": 0,
    "variacao_mensal": 0.0
  },
  {
    "id": "Alto_Alegre_Homicídio_Doloso_2026_Janeiro",
    "regiao": "Araçatuba",
    "municipio": "Alto Alegre",
    "tipo_crime": "Homicídio Doloso",
    "ano": "2026",
    "mes": "Janeiro",
    "ocorrencias": 0,
    "variacao_mensal": 0.0
  },
  {
    "id": "Alto_Alegre_Homicídio_Doloso_2026_Abril",
    "regiao": "Araçatuba",
    "municipio": "Alto Alegre",
    "tipo_crime": "Homicídio Doloso",
    "ano": "2026",
    "mes": "Abril",
    "ocorrencias": 0,
    "variacao_mensal": 0.0
  },
  {
    "id": "Alto_Alegre_Homicídio_Doloso_2026_Julho",
    "regiao": "Araçatuba",
    "municipio": "Alto Alegre",
    "tipo_crime": "Homicídio Doloso",
    "ano": "2026",
    "mes": "Julho",
    "ocorrencias": 0,
    "variacao_mensal": 0.0
  },
  {
    "id": "Alto_Alegre_Homicídio_Doloso_2026_Outubro",
    "regiao": "Araçatuba",
    "municipio": "Alto Alegre",
    "tipo_crime": "Homicídio Doloso",
    "ano": "2026",
    "mes": "Outubro",
    "ocorrencias": 0,
    "variacao_mensal": 0.0
  },
  {
    "id": "Alto_Alegre_Homicídio_Doloso_Por_Acidente_De_Trânsito_2026_Janeiro",
    "regiao": "Araçatuba",
    "municipio": "Alto Alegre",
    "tipo_crime": "Homicídio Doloso Por Acidente De Trânsito",
    "ano": "2026",
    "mes": "Janeiro",
    "ocorrencias": 0,
    "variacao_mensal": 0.0
  },
  {
    "id": "Alto_Alegre_Homicídio_Doloso_Por_Acidente_De_Trânsito_2026_Abril",
    "regiao": "Araçatuba",
    "municipio": "Alto Alegre",
    "tipo_crime": "Homicídio Doloso Por Acidente De Trânsito",
    "ano": "2026",
    "mes": "Abril",
    "ocorrencias": 0,
    "variacao_mensal": 0.0
  },
  {
    "id": "Alto_Alegre_Homicídio_Doloso_Por_Acidente_De_Trânsito_2026_Julho",
    "regiao": "Araçatuba",
    "municipio": "Alto Alegre",
    "tipo_crime": "Homicídio Doloso Por Acidente De Trânsito",
    "ano": "2026",
    "mes": "Julho",
    "ocorrencias": 0,
    "variacao_mensal": 0.0
  },
  {
    "id": "Alto_Alegre_Homicídio_Doloso_Por_Acidente_De_Trânsito_2026_Outubro",
    "regiao": "Araçatuba",
    "municipio": "Alto Alegre",
    "tipo_crime": "Homicídio Doloso Por Acidente De Trânsito",
    "ano": "2026",
    "mes": "Outubro",
    "ocorrencias": 0,
    "variacao_mensal": 0.0
  },
  {
    "id": "Alto_Alegre_Latrocínio_2026_Janeiro",
    "regiao": "Araçatuba",
    "municipio": "Alto Alegre",
    "tipo_crime": "Latrocínio",
    "ano": "2026",
    "mes": "Janeiro",
    "ocorrencias": 0,
    "variacao_mensal": 0.0
  },
  {
    "id": "Alto_Alegre_Latrocínio_2026_Abril",
    "regiao": "Araçatuba",
    "municipio": "Alto Alegre",
    "tipo_crime": "Latrocínio",
    "ano": "2026",
    "mes": "Abril",
    "ocorrencias": 0,
    "variacao_mensal": 0.0
  },
  {
    "id": "Alto_Alegre_Latrocínio_2026_Julho",
    "regiao": "Araçatuba",
    "municipio": "Alto Alegre",
    "tipo_crime": "Latrocínio",
    "ano": "2026",
    "mes": "Julho",
    "ocorrencias": 0,
    "variacao_mensal": 0.0
  },
  {
    "id": "Alto_Alegre_Latrocínio_2026_Outubro",
    "regiao": "Araçatuba",
    "municipio": "Alto Alegre",
    "tipo_crime": "Latrocínio",
    "ano": "2026",
    "mes": "Outubro",
    "ocorrencias": 0,
    "variacao_mensal": 0.0
  },
  {
    "id": "Alto_Alegre_Lesão_Corporal_Culposa_-_Outras_2026_Janeiro",
    "regiao": "Araçatuba",
    "municipio": "Alto Alegre",
    "tipo_crime": "Lesão Corporal Culposa - Outras",
    "ano": "2026",
    "mes": "Janeiro",
    "ocorrencias": 0,
    "variacao_mensal": 0.0
  },
  {
    "id": "Alto_Alegre_Lesão_Corporal_Culposa_-_Outras_2026_Abril",
    "regiao": "Araçatuba",
    "municipio": "Alto Alegre",
    "tipo_crime": "Lesão Corporal Culposa - Outras",
    "ano": "2026",
    "mes": "Abril",
    "ocorrencias": 0,
    "variacao_mensal": 0.0
  },
  {
    "id": "Alto_Alegre_Lesão_Corporal_Culposa_-_Outras_2026_Julho",
    "regiao": "Araçatuba",
    "municipio": "Alto Alegre",
    "tipo_crime": "Lesão Corporal Culposa - Outras",
    "ano": "2026",
    "mes": "Julho",
    "ocorrencias": 0,
    "variacao_mensal": 0.0
  },
  {
    "id": "Alto_Alegre_Lesão_Corporal_Culposa_-_Outras_2026_Outubro",
    "regiao": "Araçatuba",
    "municipio": "Alto Alegre",
    "tipo_crime": "Lesão Corporal Culposa - Outras",
    "ano": "2026",
    "mes": "Outubro",
    "ocorrencias": 0,
    "variacao_mensal": 0.0
  },
  {
    "id": "Alto_Alegre_Lesão_Corporal_Culposa_Por_Acidente_De_Trânsito_2026_Janeiro",
    "regiao": "Araçatuba",
    "municipio": "Alto Alegre",
    "tipo_crime": "Lesão Corporal Culposa Por Acidente De Trânsito",
    "ano": "2026",
    "mes": "Janeiro",
    "ocorrencias": 0,
    "variacao_mensal": 0.0
  },
  {
    "id": "Alto_Alegre_Lesão_Corporal_Culposa_Por_Acidente_De_Trânsito_2026_Abril",
    "regiao": "Araçatuba",
    "municipio": "Alto Alegre",
    "tipo_crime": "Lesão Corporal Culposa Por Acidente De Trânsito",
    "ano": "2026",
    "mes": "Abril",
    "ocorrencias": 0,
    "variacao_mensal": 0.0
  },
  {
    "id": "Alto_Alegre_Lesão_Corporal_Culposa_Por_Acidente_De_Trânsito_2026_Julho",
    "regiao": "Araçatuba",
    "municipio": "Alto Alegre",
    "tipo_crime": "Lesão Corporal Culposa Por Acidente De Trânsito",
    "ano": "2026",
    "mes": "Julho",
    "ocorrencias": 0,
    "variacao_mensal": 0.0
  },
  {
    "id": "Alto_Alegre_Lesão_Corporal_Culposa_Por_Acidente_De_Trânsito_2026_Outubro",
    "regiao": "Araçatuba",
    "municipio": "Alto Alegre",
    "tipo_crime": "Lesão Corporal Culposa Por Acidente De Trânsito",
    "ano": "2026",
    "mes": "Outubro",
    "ocorrencias": 0,
    "variacao_mensal": 0.0
  },
  {
    "id": "Alto_Alegre_Lesão_Corporal_Dolosa_2026_Janeiro",
    "regiao": "Araçatuba",
    "municipio": "Alto Alegre",
    "tipo_crime": "Lesão Corporal Dolosa",
    "ano": "2026",
    "mes": "Janeiro",
    "ocorrencias": 0,
    "variacao_mensal": 0.0
  },
  {
    "id": "Alto_Alegre_Lesão_Corporal_Dolosa_2026_Abril",
    "regiao": "Araçatuba",
    "municipio": "Alto Alegre",
    "tipo_crime": "Lesão Corporal Dolosa",
    "ano": "2026",
    "mes": "Abril",
    "ocorrencias": 0,
    "variacao_mensal": 0.0
  },
  {
    "id": "Alto_Alegre_Lesão_Corporal_Dolosa_2026_Julho",
    "regiao": "Araçatuba",
    "municipio": "Alto Alegre",
    "tipo_crime": "Lesão Corporal Dolosa",
    "ano": "2026",
    "mes": "Julho",
    "ocorrencias": 0,
    "variacao_mensal": 0.0
  },
  {
    "id": "Alto_Alegre_Lesão_Corporal_Dolosa_2026_Outubro",
    "regiao": "Araçatuba",
    "municipio": "Alto Alegre",
    "tipo_crime": "Lesão Corporal Dolosa",
    "ano": "2026",
    "mes": "Outubro",
    "ocorrencias": 0,
    "variacao_mensal": 0.0
  },
  {
    "id": "Alto_Alegre_Lesão_Corporal_Seguida_De_Morte_2026_Janeiro",
    "regiao": "Araçatuba",
    "municipio": "Alto Alegre",
    "tipo_crime": "Lesão Corporal Seguida De Morte",
    "ano": "2026",
    "mes": "Janeiro",
    "ocorrencias": 0,
    "variacao_mensal": 0.0
  },
  {
    "id": "Alto_Alegre_Lesão_Corporal_Seguida_De_Morte_2026_Abril",
    "regiao": "Araçatuba",
    "municipio": "Alto Alegre",
    "tipo_crime": "Lesão Corporal Seguida De Morte",
    "ano": "2026",
    "mes": "Abril",
    "ocorrencias": 0,
    "variacao_mensal": 0.0
  },
  {
    "id": "Alto_Alegre_Lesão_Corporal_Seguida_De_Morte_2026_Julho",
    "regiao": "Araçatuba",
    "municipio": "Alto Alegre",
    "tipo_crime": "Lesão Corporal Seguida De Morte",
    "ano": "2026",
    "mes": "Julho",
    "ocorrencias": 0,
    "variacao_mensal": 0.0
  },
  {
    "id": "Alto_Alegre_Lesão_Corporal_Seguida_De_Morte_2026_Outubro",
    "regiao": "Araçatuba",
    "municipio": "Alto Alegre",
    "tipo_crime": "Lesão Corporal Seguida De Morte",
    "ano": "2026",
    "mes": "Outubro",
    "ocorrencias": 0,
    "variacao_mensal": 0.0
  },
  {
    "id": "Alto_Alegre_Roubo_-_Outros_2026_Janeiro",
    "regiao": "Araçatuba",
    "municipio": "Alto Alegre",
    "tipo_crime": "Roubo - Outros",
    "ano": "2026",
    "mes": "Janeiro",
    "ocorrencias": 0,
    "variacao_mensal": 0.0
  },
  {
    "id": "Alto_Alegre_Roubo_-_Outros_2026_Abril",
    "regiao": "Araçatuba",
    "municipio": "Alto Alegre",
    "tipo_crime": "Roubo - Outros",
    "ano": "2026",
    "mes": "Abril",
    "ocorrencias": 0,
    "variacao_mensal": 0.0
  },
  {
    "id": "Alto_Alegre_Roubo_-_Outros_2026_Julho",
    "regiao": "Araçatuba",
    "municipio": "Alto Alegre",
    "tipo_crime": "Roubo - Outros",
    "ano": "2026",
    "mes": "Julho",
    "ocorrencias": 0,
    "variacao_mensal": 0.0
  },
  {
    "id": "Alto_Alegre_Roubo_-_Outros_2026_Outubro",
    "regiao": "Araçatuba",
    "municipio": "Alto Alegre",
    "tipo_crime": "Roubo - Outros",
    "ano": "2026",
    "mes": "Outubro",
    "ocorrencias": 0,
    "variacao_mensal": 0.0
  },
  {
    "id": "Alto_Alegre_Roubo_A_Banco_2026_Janeiro",
    "regiao": "Araçatuba",
    "municipio": "Alto Alegre",
    "tipo_crime": "Roubo A Banco",
    "ano": "2026",
    "mes": "Janeiro",
    "ocorrencias": 0,
    "variacao_mensal": 0.0
  },
  {
    "id": "Alto_Alegre_Roubo_A_Banco_2026_Abril",
    "regiao": "Araçatuba",
    "municipio": "Alto Alegre",
    "tipo_crime": "Roubo A Banco",
    "ano": "2026",
    "mes": "Abril",
    "ocorrencias": 0,
    "variacao_mensal": 0.0
  },
  {
    "id": "Alto_Alegre_Roubo_A_Banco_2026_Julho",
    "regiao": "Araçatuba",
    "municipio": "Alto Alegre",
    "tipo_crime": "Roubo A Banco",
    "ano": "2026",
    "mes": "Julho",
    "ocorrencias": 0,
    "variacao_mensal": 0.0
  },
  {
    "id": "Alto_Alegre_Roubo_A_Banco_2026_Outubro",
    "regiao": "Araçatuba",
    "municipio": "Alto Alegre",
    "tipo_crime": "Roubo A Banco",
    "ano": "2026",
    "mes": "Outubro",
    "ocorrencias": 0,
    "variacao_mensal": 0.0
  },
  {
    "id": "Alto_Alegre_Roubo_De_Carga_2026_Janeiro",
    "regiao": "Araçatuba",
    "municipio": "Alto Alegre",
    "tipo_crime": "Roubo De Carga",
    "ano": "2026",
    "mes": "Janeiro",
    "ocorrencias": 0,
    "variacao_mensal": 0.0
  },
  {
    "id": "Alto_Alegre_Roubo_De_Carga_2026_Abril",
    "regiao": "Araçatuba",
    "municipio": "Alto Alegre",
    "tipo_crime": "Roubo De Carga",
    "ano": "2026",
    "mes": "Abril",
    "ocorrencias": 0,
    "variacao_mensal": 0.0
  },
  {
    "id": "Alto_Alegre_Roubo_De_Carga_2026_Julho",
    "regiao": "Araçatuba",
    "municipio": "Alto Alegre",
    "tipo_crime": "Roubo De Carga",
    "ano": "2026",
    "mes": "Julho",
    "ocorrencias": 0,
    "variacao_mensal": 0.0
  },
  {
    "id": "Alto_Alegre_Roubo_De_Carga_2026_Outubro",
    "regiao": "Araçatuba",
    "municipio": "Alto Alegre",
    "tipo_crime": "Roubo De Carga",
    "ano": "2026",
    "mes": "Outubro",
    "ocorrencias": 0,
    "variacao_mensal": 0.0
  },
  {
    "id": "Alto_Alegre_Roubo_De_Veículo_2026_Janeiro",
    "regiao": "Araçatuba",
    "municipio": "Alto Alegre",
    "tipo_crime": "Roubo De Veículo",
    "ano": "2026",
    "mes": "Janeiro",
    "ocorrencias": 0,
    "variacao_mensal": 0.0
  },
  {
    "id": "Alto_Alegre_Roubo_De_Veículo_2026_Abril",
    "regiao": "Araçatuba",
    "municipio": "Alto Alegre",
    "tipo_crime": "Roubo De Veículo",
    "ano": "2026",
    "mes": "Abril",
    "ocorrencias": 0,
    "variacao_mensal": 0.0
  },
  {
    "id": "Alto_Alegre_Roubo_De_Veículo_2026_Julho",
    "regiao": "Araçatuba",
    "municipio": "Alto Alegre",
    "tipo_crime": "Roubo De Veículo",
    "ano": "2026",
    "mes": "Julho",
    "ocorrencias": 0,
    "variacao_mensal": 0.0
  },
  {
    "id": "Alto_Alegre_Roubo_De_Veículo_2026_Outubro",
    "regiao": "Araçatuba",
    "municipio": "Alto Alegre",
    "tipo_crime": "Roubo De Veículo",
    "ano": "2026",
    "mes": "Outubro",
    "ocorrencias": 0,
    "variacao_mensal": 0.0
  },
  {
    "id": "Alto_Alegre_Tentativa_De_Homicídio_2026_Janeiro",
    "regiao": "Araçatuba",
    "municipio": "Alto Alegre",
    "tipo_crime": "Tentativa De Homicídio",
    "ano": "2026",
    "mes": "Janeiro",
    "ocorrencias": 0,
    "variacao_mensal": 0.0
  },
  {
    "id": "Alto_Alegre_Tentativa_De_Homicídio_2026_Abril",
    "regiao": "Araçatuba",
    "municipio": "Alto Alegre",
    "tipo_crime": "Tentativa De Homicídio",
    "ano": "2026",
    "mes": "Abril",
    "ocorrencias": 0,
    "variacao_mensal": 0.0
  },
  {
    "id": "Alto_Alegre_Tentativa_De_Homicídio_2026_Julho",
    "regiao": "Araçatuba",
    "municipio": "Alto Alegre",
    "tipo_crime": "Tentativa De Homicídio",
    "ano": "2026",
    "mes": "Julho",
    "ocorrencias": 0,
    "variacao_mensal": 0.0
  },
  {
    "id": "Alto_Alegre_Tentativa_De_Homicídio_2026_Outubro",
    "regiao": "Araçatuba",
    "municipio": "Alto Alegre",
    "tipo_crime": "Tentativa De Homicídio",
    "ano": "2026",
    "mes": "Outubro",
    "ocorrencias": 0,
    "variacao_mensal": 0.0
  },
  {
    "id": "Andradina_Estupro_2026_Janeiro",
    "regiao": "Araçatuba",
    "municipio": "Andradina",
    "tipo_crime": "Estupro",
    "ano": "2026",
    "mes": "Janeiro",
    "ocorrencias": 0,
    "variacao_mensal": 0.0
  },
  {
    "id": "Andradina_Estupro_2026_Abril",
    "regiao": "Araçatuba",
    "municipio": "Andradina",
    "tipo_crime": "Estupro",
    "ano": "2026",
    "mes": "Abril",
    "ocorrencias": 2,
    "variacao_mensal": 0.0
  },
  {
    "id": "Andradina_Estupro_2026_Julho",
    "regiao": "Araçatuba",
    "municipio": "Andradina",
    "tipo_crime": "Estupro",
    "ano": "2026",
    "mes": "Julho",
    "ocorrencias": 0,
    "variacao_mensal": -100.0
  },
  {
    "id": "Andradina_Estupro_2026_Outubro",
    "regiao": "Araçatuba",
    "municipio": "Andradina",
    "tipo_crime": "Estupro",
    "ano": "2026",
    "mes": "Outubro",
    "ocorrencias": 0,
    "variacao_mensal": 0.0
  },
  {
    "id": "Andradina_Estupro_De_Vulnerável_2026_Janeiro",
    "regiao": "Araçatuba",
    "municipio": "Andradina",
    "tipo_crime": "Estupro De Vulnerável",
    "ano": "2026",
    "mes": "Janeiro",
    "ocorrencias": 2,
    "variacao_mensal": 0.0
  },
  {
    "id": "Andradina_Estupro_De_Vulnerável_2026_Abril",
    "regiao": "Araçatuba",
    "municipio": "Andradina",
    "tipo_crime": "Estupro De Vulnerável",
    "ano": "2026",
    "mes": "Abril",
    "ocorrencias": 2,
    "variacao_mensal": 0.0
  },
  {
    "id": "Andradina_Estupro_De_Vulnerável_2026_Julho",
    "regiao": "Araçatuba",
    "municipio": "Andradina",
    "tipo_crime": "Estupro De Vulnerável",
    "ano": "2026",
    "mes": "Julho",
    "ocorrencias": 0,
    "variacao_mensal": -100.0
  },
  {
    "id": "Andradina_Estupro_De_Vulnerável_2026_Outubro",
    "regiao": "Araçatuba",
    "municipio": "Andradina",
    "tipo_crime": "Estupro De Vulnerável",
    "ano": "2026",
    "mes": "Outubro",
    "ocorrencias": 0,
    "variacao_mensal": 0.0
  },
  {
    "id": "Andradina_Furto_-_Outros_2026_Janeiro",
    "regiao": "Araçatuba",
    "municipio": "Andradina",
    "tipo_crime": "Furto - Outros",
    "ano": "2026",
    "mes": "Janeiro",
    "ocorrencias": 36,
    "variacao_mensal": 0.0
  },
  {
    "id": "Andradina_Furto_-_Outros_2026_Abril",
    "regiao": "Araçatuba",
    "municipio": "Andradina",
    "tipo_crime": "Furto - Outros",
    "ano": "2026",
    "mes": "Abril",
    "ocorrencias": 48,
    "variacao_mensal": 33.33
  },
  {
    "id": "Andradina_Furto_-_Outros_2026_Julho",
    "regiao": "Araçatuba",
    "municipio": "Andradina",
    "tipo_crime": "Furto - Outros",
    "ano": "2026",
    "mes": "Julho",
    "ocorrencias": 0,
    "variacao_mensal": -100.0
  },
  {
    "id": "Andradina_Furto_-_Outros_2026_Outubro",
    "regiao": "Araçatuba",
    "municipio": "Andradina",
    "tipo_crime": "Furto - Outros",
    "ano": "2026",
    "mes": "Outubro",
    "ocorrencias": 0,
    "variacao_mensal": 0.0
  },
  {
    "id": "Andradina_Furto_De_Veículo_2026_Janeiro",
    "regiao": "Araçatuba",
    "municipio": "Andradina",
    "tipo_crime": "Furto De Veículo",
    "ano": "2026",
    "mes": "Janeiro",
    "ocorrencias": 2,
    "variacao_mensal": 0.0
  },
  {
    "id": "Andradina_Furto_De_Veículo_2026_Abril",
    "regiao": "Araçatuba",
    "municipio": "Andradina",
    "tipo_crime": "Furto De Veículo",
    "ano": "2026",
    "mes": "Abril",
    "ocorrencias": 0,
    "variacao_mensal": -100.0
  },
  {
    "id": "Andradina_Furto_De_Veículo_2026_Julho",
    "regiao": "Araçatuba",
    "municipio": "Andradina",
    "tipo_crime": "Furto De Veículo",
    "ano": "2026",
    "mes": "Julho",
    "ocorrencias": 0,
    "variacao_mensal": 0.0
  },
  {
    "id": "Andradina_Furto_De_Veículo_2026_Outubro",
    "regiao": "Araçatuba",
    "municipio": "Andradina",
    "tipo_crime": "Furto De Veículo",
    "ano": "2026",
    "mes": "Outubro",
    "ocorrencias": 0,
    "variacao_mensal": 0.0
  },
  {
    "id": "Andradina_Homicídio_Culposo_Outros_2026_Janeiro",
    "regiao": "Araçatuba",
    "municipio": "Andradina",
    "tipo_crime": "Homicídio Culposo Outros",
    "ano": "2026",
    "mes": "Janeiro",
    "ocorrencias": 0,
    "variacao_mensal": 0.0
  },
  {
    "id": "Andradina_Homicídio_Culposo_Outros_2026_Abril",
    "regiao": "Araçatuba",
    "municipio": "Andradina",
    "tipo_crime": "Homicídio Culposo Outros",
    "ano": "2026",
    "mes": "Abril",
    "ocorrencias": 0,
    "variacao_mensal": 0.0
  },
  {
    "id": "Andradina_Homicídio_Culposo_Outros_2026_Julho",
    "regiao": "Araçatuba",
    "municipio": "Andradina",
    "tipo_crime": "Homicídio Culposo Outros",
    "ano": "2026",
    "mes": "Julho",
    "ocorrencias": 0,
    "variacao_mensal": 0.0
  },
  {
    "id": "Andradina_Homicídio_Culposo_Outros_2026_Outubro",
    "regiao": "Araçatuba",
    "municipio": "Andradina",
    "tipo_crime": "Homicídio Culposo Outros",
    "ano": "2026",
    "mes": "Outubro",
    "ocorrencias": 0,
    "variacao_mensal": 0.0
  },
  {
    "id": "Andradina_Homicídio_Culposo_Por_Acidente_De_Trânsito_2026_Janeiro",
    "regiao": "Araçatuba",
    "municipio": "Andradina",
    "tipo_crime": "Homicídio Culposo Por Acidente De Trânsito",
    "ano": "2026",
    "mes": "Janeiro",
    "ocorrencias": 0,
    "variacao_mensal": 0.0
  },
  {
    "id": "Andradina_Homicídio_Culposo_Por_Acidente_De_Trânsito_2026_Abril",
    "regiao": "Araçatuba",
    "municipio": "Andradina",
    "tipo_crime": "Homicídio Culposo Por Acidente De Trânsito",
    "ano": "2026",
    "mes": "Abril",
    "ocorrencias": 0,
    "variacao_mensal": 0.0
  },
  {
    "id": "Andradina_Homicídio_Culposo_Por_Acidente_De_Trânsito_2026_Julho",
    "regiao": "Araçatuba",
    "municipio": "Andradina",
    "tipo_crime": "Homicídio Culposo Por Acidente De Trânsito",
    "ano": "2026",
    "mes": "Julho",
    "ocorrencias": 0,
    "variacao_mensal": 0.0
  },
  {
    "id": "Andradina_Homicídio_Culposo_Por_Acidente_De_Trânsito_2026_Outubro",
    "regiao": "Araçatuba",
    "municipio": "Andradina",
    "tipo_crime": "Homicídio Culposo Por Acidente De Trânsito",
    "ano": "2026",
    "mes": "Outubro",
    "ocorrencias": 0,
    "variacao_mensal": 0.0
  },
  {
    "id": "Andradina_Homicídio_Doloso_2026_Janeiro",
    "regiao": "Araçatuba",
    "municipio": "Andradina",
    "tipo_crime": "Homicídio Doloso",
    "ano": "2026",
    "mes": "Janeiro",
    "ocorrencias": 1,
    "variacao_mensal": 0.0
  },
  {
    "id": "Andradina_Homicídio_Doloso_2026_Abril",
    "regiao": "Araçatuba",
    "municipio": "Andradina",
    "tipo_crime": "Homicídio Doloso",
    "ano": "2026",
    "mes": "Abril",
    "ocorrencias": 1,
    "variacao_mensal": 0.0
  },
  {
    "id": "Andradina_Homicídio_Doloso_2026_Julho",
    "regiao": "Araçatuba",
    "municipio": "Andradina",
    "tipo_crime": "Homicídio Doloso",
    "ano": "2026",
    "mes": "Julho",
    "ocorrencias": 0,
    "variacao_mensal": -100.0
  },
  {
    "id": "Andradina_Homicídio_Doloso_2026_Outubro",
    "regiao": "Araçatuba",
    "municipio": "Andradina",
    "tipo_crime": "Homicídio Doloso",
    "ano": "2026",
    "mes": "Outubro",
    "ocorrencias": 0,
    "variacao_mensal": 0.0
  },
  {
    "id": "Andradina_Homicídio_Doloso_Por_Acidente_De_Trânsito_2026_Janeiro",
    "regiao": "Araçatuba",
    "municipio": "Andradina",
    "tipo_crime": "Homicídio Doloso Por Acidente De Trânsito",
    "ano": "2026",
    "mes": "Janeiro",
    "ocorrencias": 0,
    "variacao_mensal": 0.0
  },
  {
    "id": "Andradina_Homicídio_Doloso_Por_Acidente_De_Trânsito_2026_Abril",
    "regiao": "Araçatuba",
    "municipio": "Andradina",
    "tipo_crime": "Homicídio Doloso Por Acidente De Trânsito",
    "ano": "2026",
    "mes": "Abril",
    "ocorrencias": 0,
    "variacao_mensal": 0.0
  },
  {
    "id": "Andradina_Homicídio_Doloso_Por_Acidente_De_Trânsito_2026_Julho",
    "regiao": "Araçatuba",
    "municipio": "Andradina",
    "tipo_crime": "Homicídio Doloso Por Acidente De Trânsito",
    "ano": "2026",
    "mes": "Julho",
    "ocorrencias": 0,
    "variacao_mensal": 0.0
  },
  {
    "id": "Andradina_Homicídio_Doloso_Por_Acidente_De_Trânsito_2026_Outubro",
    "regiao": "Araçatuba",
    "municipio": "Andradina",
    "tipo_crime": "Homicídio Doloso Por Acidente De Trânsito",
    "ano": "2026",
    "mes": "Outubro",
    "ocorrencias": 0,
    "variacao_mensal": 0.0
  },
  {
    "id": "Andradina_Latrocínio_2026_Janeiro",
    "regiao": "Araçatuba",
    "municipio": "Andradina",
    "tipo_crime": "Latrocínio",
    "ano": "2026",
    "mes": "Janeiro",
    "ocorrencias": 0,
    "variacao_mensal": 0.0
  },
  {
    "id": "Andradina_Latrocínio_2026_Abril",
    "regiao": "Araçatuba",
    "municipio": "Andradina",
    "tipo_crime": "Latrocínio",
    "ano": "2026",
    "mes": "Abril",
    "ocorrencias": 0,
    "variacao_mensal": 0.0
  },
  {
    "id": "Andradina_Latrocínio_2026_Julho",
    "regiao": "Araçatuba",
    "municipio": "Andradina",
    "tipo_crime": "Latrocínio",
    "ano": "2026",
    "mes": "Julho",
    "ocorrencias": 0,
    "variacao_mensal": 0.0
  },
  {
    "id": "Andradina_Latrocínio_2026_Outubro",
    "regiao": "Araçatuba",
    "municipio": "Andradina",
    "tipo_crime": "Latrocínio",
    "ano": "2026",
    "mes": "Outubro",
    "ocorrencias": 0,
    "variacao_mensal": 0.0
  },
  {
    "id": "Andradina_Lesão_Corporal_Culposa_-_Outras_2026_Janeiro",
    "regiao": "Araçatuba",
    "municipio": "Andradina",
    "tipo_crime": "Lesão Corporal Culposa - Outras",
    "ano": "2026",
    "mes": "Janeiro",
    "ocorrencias": 1,
    "variacao_mensal": 0.0
  },
  {
    "id": "Andradina_Lesão_Corporal_Culposa_-_Outras_2026_Abril",
    "regiao": "Araçatuba",
    "municipio": "Andradina",
    "tipo_crime": "Lesão Corporal Culposa - Outras",
    "ano": "2026",
    "mes": "Abril",
    "ocorrencias": 0,
    "variacao_mensal": -100.0
  },
  {
    "id": "Andradina_Lesão_Corporal_Culposa_-_Outras_2026_Julho",
    "regiao": "Araçatuba",
    "municipio": "Andradina",
    "tipo_crime": "Lesão Corporal Culposa - Outras",
    "ano": "2026",
    "mes": "Julho",
    "ocorrencias": 0,
    "variacao_mensal": 0.0
  },
  {
    "id": "Andradina_Lesão_Corporal_Culposa_-_Outras_2026_Outubro",
    "regiao": "Araçatuba",
    "municipio": "Andradina",
    "tipo_crime": "Lesão Corporal Culposa - Outras",
    "ano": "2026",
    "mes": "Outubro",
    "ocorrencias": 0,
    "variacao_mensal": 0.0
  },
  {
    "id": "Andradina_Lesão_Corporal_Culposa_Por_Acidente_De_Trânsito_2026_Janeiro",
    "regiao": "Araçatuba",
    "municipio": "Andradina",
    "tipo_crime": "Lesão Corporal Culposa Por Acidente De Trânsito",
    "ano": "2026",
    "mes": "Janeiro",
    "ocorrencias": 22,
    "variacao_mensal": 0.0
  },
  {
    "id": "Andradina_Lesão_Corporal_Culposa_Por_Acidente_De_Trânsito_2026_Abril",
    "regiao": "Araçatuba",
    "municipio": "Andradina",
    "tipo_crime": "Lesão Corporal Culposa Por Acidente De Trânsito",
    "ano": "2026",
    "mes": "Abril",
    "ocorrencias": 20,
    "variacao_mensal": -9.09
  },
  {
    "id": "Andradina_Lesão_Corporal_Culposa_Por_Acidente_De_Trânsito_2026_Julho",
    "regiao": "Araçatuba",
    "municipio": "Andradina",
    "tipo_crime": "Lesão Corporal Culposa Por Acidente De Trânsito",
    "ano": "2026",
    "mes": "Julho",
    "ocorrencias": 0,
    "variacao_mensal": -100.0
  },
  {
    "id": "Andradina_Lesão_Corporal_Culposa_Por_Acidente_De_Trânsito_2026_Outubro",
    "regiao": "Araçatuba",
    "municipio": "Andradina",
    "tipo_crime": "Lesão Corporal Culposa Por Acidente De Trânsito",
    "ano": "2026",
    "mes": "Outubro",
    "ocorrencias": 0,
    "variacao_mensal": 0.0
  },
  {
    "id": "Andradina_Lesão_Corporal_Dolosa_2026_Janeiro",
    "regiao": "Araçatuba",
    "municipio": "Andradina",
    "tipo_crime": "Lesão Corporal Dolosa",
    "ano": "2026",
    "mes": "Janeiro",
    "ocorrencias": 13,
    "variacao_mensal": 0.0
  },
  {
    "id": "Andradina_Lesão_Corporal_Dolosa_2026_Abril",
    "regiao": "Araçatuba",
    "municipio": "Andradina",
    "tipo_crime": "Lesão Corporal Dolosa",
    "ano": "2026",
    "mes": "Abril",
    "ocorrencias": 17,
    "variacao_mensal": 30.77
  },
  {
    "id": "Andradina_Lesão_Corporal_Dolosa_2026_Julho",
    "regiao": "Araçatuba",
    "municipio": "Andradina",
    "tipo_crime": "Lesão Corporal Dolosa",
    "ano": "2026",
    "mes": "Julho",
    "ocorrencias": 0,
    "variacao_mensal": -100.0
  },
  {
    "id": "Andradina_Lesão_Corporal_Dolosa_2026_Outubro",
    "regiao": "Araçatuba",
    "municipio": "Andradina",
    "tipo_crime": "Lesão Corporal Dolosa",
    "ano": "2026",
    "mes": "Outubro",
    "ocorrencias": 0,
    "variacao_mensal": 0.0
  },
  {
    "id": "Andradina_Lesão_Corporal_Seguida_De_Morte_2026_Janeiro",
    "regiao": "Araçatuba",
    "municipio": "Andradina",
    "tipo_crime": "Lesão Corporal Seguida De Morte",
    "ano": "2026",
    "mes": "Janeiro",
    "ocorrencias": 0,
    "variacao_mensal": 0.0
  },
  {
    "id": "Andradina_Lesão_Corporal_Seguida_De_Morte_2026_Abril",
    "regiao": "Araçatuba",
    "municipio": "Andradina",
    "tipo_crime": "Lesão Corporal Seguida De Morte",
    "ano": "2026",
    "mes": "Abril",
    "ocorrencias": 0,
    "variacao_mensal": 0.0
  },
  {
    "id": "Andradina_Lesão_Corporal_Seguida_De_Morte_2026_Julho",
    "regiao": "Araçatuba",
    "municipio": "Andradina",
    "tipo_crime": "Lesão Corporal Seguida De Morte",
    "ano": "2026",
    "mes": "Julho",
    "ocorrencias": 0,
    "variacao_mensal": 0.0
  },
  {
    "id": "Andradina_Lesão_Corporal_Seguida_De_Morte_2026_Outubro",
    "regiao": "Araçatuba",
    "municipio": "Andradina",
    "tipo_crime": "Lesão Corporal Seguida De Morte",
    "ano": "2026",
    "mes": "Outubro",
    "ocorrencias": 0,
    "variacao_mensal": 0.0
  },
  {
    "id": "Andradina_Roubo_-_Outros_2026_Janeiro",
    "regiao": "Araçatuba",
    "municipio": "Andradina",
    "tipo_crime": "Roubo - Outros",
    "ano": "2026",
    "mes": "Janeiro",
    "ocorrencias": 0,
    "variacao_mensal": 0.0
  },
  {
    "id": "Andradina_Roubo_-_Outros_2026_Abril",
    "regiao": "Araçatuba",
    "municipio": "Andradina",
    "tipo_crime": "Roubo - Outros",
    "ano": "2026",
    "mes": "Abril",
    "ocorrencias": 3,
    "variacao_mensal": 0.0
  },
  {
    "id": "Andradina_Roubo_-_Outros_2026_Julho",
    "regiao": "Araçatuba",
    "municipio": "Andradina",
    "tipo_crime": "Roubo - Outros",
    "ano": "2026",
    "mes": "Julho",
    "ocorrencias": 0,
    "variacao_mensal": -100.0
  },
  {
    "id": "Andradina_Roubo_-_Outros_2026_Outubro",
    "regiao": "Araçatuba",
    "municipio": "Andradina",
    "tipo_crime": "Roubo - Outros",
    "ano": "2026",
    "mes": "Outubro",
    "ocorrencias": 0,
    "variacao_mensal": 0.0
  },
  {
    "id": "Andradina_Roubo_A_Banco_2026_Janeiro",
    "regiao": "Araçatuba",
    "municipio": "Andradina",
    "tipo_crime": "Roubo A Banco",
    "ano": "2026",
    "mes": "Janeiro",
    "ocorrencias": 0,
    "variacao_mensal": 0.0
  },
  {
    "id": "Andradina_Roubo_A_Banco_2026_Abril",
    "regiao": "Araçatuba",
    "municipio": "Andradina",
    "tipo_crime": "Roubo A Banco",
    "ano": "2026",
    "mes": "Abril",
    "ocorrencias": 0,
    "variacao_mensal": 0.0
  },
  {
    "id": "Andradina_Roubo_A_Banco_2026_Julho",
    "regiao": "Araçatuba",
    "municipio": "Andradina",
    "tipo_crime": "Roubo A Banco",
    "ano": "2026",
    "mes": "Julho",
    "ocorrencias": 0,
    "variacao_mensal": 0.0
  },
  {
    "id": "Andradina_Roubo_A_Banco_2026_Outubro",
    "regiao": "Araçatuba",
    "municipio": "Andradina",
    "tipo_crime": "Roubo A Banco",
    "ano": "2026",
    "mes": "Outubro",
    "ocorrencias": 0,
    "variacao_mensal": 0.0
  },
  {
    "id": "Andradina_Roubo_De_Carga_2026_Janeiro",
    "regiao": "Araçatuba",
    "municipio": "Andradina",
    "tipo_crime": "Roubo De Carga",
    "ano": "2026",
    "mes": "Janeiro",
    "ocorrencias": 0,
    "variacao_mensal": 0.0
  },
  {
    "id": "Andradina_Roubo_De_Carga_2026_Abril",
    "regiao": "Araçatuba",
    "municipio": "Andradina",
    "tipo_crime": "Roubo De Carga",
    "ano": "2026",
    "mes": "Abril",
    "ocorrencias": 0,
    "variacao_mensal": 0.0
  },
  {
    "id": "Andradina_Roubo_De_Carga_2026_Julho",
    "regiao": "Araçatuba",
    "municipio": "Andradina",
    "tipo_crime": "Roubo De Carga",
    "ano": "2026",
    "mes": "Julho",
    "ocorrencias": 0,
    "variacao_mensal": 0.0
  },
  {
    "id": "Andradina_Roubo_De_Carga_2026_Outubro",
    "regiao": "Araçatuba",
    "municipio": "Andradina",
    "tipo_crime": "Roubo De Carga",
    "ano": "2026",
    "mes": "Outubro",
    "ocorrencias": 0,
    "variacao_mensal": 0.0
  },
  {
    "id": "Andradina_Roubo_De_Veículo_2026_Janeiro",
    "regiao": "Araçatuba",
    "municipio": "Andradina",
    "tipo_crime": "Roubo De Veículo",
    "ano": "2026",
    "mes": "Janeiro",
    "ocorrencias": 0,
    "variacao_mensal": 0.0
  },
  {
    "id": "Andradina_Roubo_De_Veículo_2026_Abril",
    "regiao": "Araçatuba",
    "municipio": "Andradina",
    "tipo_crime": "Roubo De Veículo",
    "ano": "2026",
    "mes": "Abril",
    "ocorrencias": 1,
    "variacao_mensal": 0.0
  },
  {
    "id": "Andradina_Roubo_De_Veículo_2026_Julho",
    "regiao": "Araçatuba",
    "municipio": "Andradina",
    "tipo_crime": "Roubo De Veículo",
    "ano": "2026",
    "mes": "Julho",
    "ocorrencias": 0,
    "variacao_mensal": -100.0
  },
  {
    "id": "Andradina_Roubo_De_Veículo_2026_Outubro",
    "regiao": "Araçatuba",
    "municipio": "Andradina",
    "tipo_crime": "Roubo De Veículo",
    "ano": "2026",
    "mes": "Outubro",
    "ocorrencias": 0,
    "variacao_mensal": 0.0
  },
  {
    "id": "Andradina_Tentativa_De_Homicídio_2026_Janeiro",
    "regiao": "Araçatuba",
    "municipio": "Andradina",
    "tipo_crime": "Tentativa De Homicídio",
    "ano": "2026",
    "mes": "Janeiro",
    "ocorrencias": 0,
    "variacao_mensal": 0.0
  },
  {
    "id": "Andradina_Tentativa_De_Homicídio_2026_Abril",
    "regiao": "Araçatuba",
    "municipio": "Andradina",
    "tipo_crime": "Tentativa De Homicídio",
    "ano": "2026",
    "mes": "Abril",
    "ocorrencias": 0,
    "variacao_mensal": 0.0
  },
  {
    "id": "Andradina_Tentativa_De_Homicídio_2026_Julho",
    "regiao": "Araçatuba",
    "municipio": "Andradina",
    "tipo_crime": "Tentativa De Homicídio",
    "ano": "2026",
    "mes": "Julho",
    "ocorrencias": 0,
    "variacao_mensal": 0.0
  },
  {
    "id": "Andradina_Tentativa_De_Homicídio_2026_Outubro",
    "regiao": "Araçatuba",
    "municipio": "Andradina",
    "tipo_crime": "Tentativa De Homicídio",
    "ano": "2026",
    "mes": "Outubro",
    "ocorrencias": 0,
    "variacao_mensal": 0.0
  }
]